Workbook

Sheet 销售与成本
A1: 日期 | B1: 销售收入（元） | C1: 销售数量（米） | D1: 产品售价（元/米） | E1: 营业成本（元） | F1: PVC树脂价格（元/吨） | G1: 单位成本（元/米） | H1: 毛利（元） | I1: 运营费用（元） | J1: 净利润（元）
A2: 44592 | B2: =C2*D2 -> 8250000 | C2: 550000 | D2: 15 | E2: 8190000 | F2: 8900 | G2: =E2/C2 -> 14.890909 | H2: =B2-E2 -> 60000 | I2: 982500 | J2: =B2-E2-I2 -> -922500
A3: 44620 | B3: =C3*D3 -> 7961200 | C3: 520000 | D3: 15.31 | E3: 7826000 | F3: 8800 | G3: =E3/C3 -> 15.05 | H3: =B3-E3 -> 135200 | I3: 978000 | J3: =B3-E3-I3 -> -842800
A4: 44651 | B4: =C4*D4 -> 8680000 | C4: 500000 | D4: 17.36 | E4: 7330000 | F4: 8500 | G4: =E4/C4 -> 14.66 | H4: =B4-E4 -> 1350000 | I4: 975000 | J4: =B4-E4-I4 -> 375000
A5: 44681 | B5: =C5*D5 -> 7492800 | C5: 480000 | D5: 15.61 | E5: 6868800 | F5: 8200 | G5: =E5/C5 -> 14.31 | H5: =B5-E5 -> 624000 | I5: 972000 | J5: =B5-E5-I5 -> -348000
A6: 44712 | B6: =C6*D6 -> 7442800 | C6: 460000 | D6: 16.18 | E6: 6595600 | F6: 7800 | G6: =E6/C6 -> 14.338261 | H6: =B6-E6 -> 847200 | I6: 969000 | J6: =B6-E6-I6 -> -121800
A7: 44742 | B7: =C7*D7 -> 7798500 | C7: 450000 | D7: 17.33 | E7: 7038000 | F7: 7400 | G7: =E7/C7 -> 15.64 | H7: =B7-E7 -> 760500 | I7: 967500 | J7: =B7-E7-I7 -> -207000
A8: 44773 | B8: =C8*D8 -> 8270800 | C8: 460000 | D8: 17.98 | E8: 6670800 | F8: 7100 | G8: =E8/C8 -> 14.501739 | H8: =B8-E8 -> 1600000 | I8: 969000 | J8: =B8-E8-I8 -> 631000
A9: 44804 | B9: =C9*D9 -> 7458900 | C9: 470000 | D9: 15.87 | E9: 6862900 | F9: 6600 | G9: =E9/C9 -> 14.601915 | H9: =B9-E9 -> 596000 | I9: 970500 | J9: =B9-E9-I9 -> -374500
A10: 44834 | B10: =C10*D10 -> 7444800 | C10: 480000 | D10: 15.51 | E10: 7128000 | F10: 6200 | G10: =E10/C10 -> 14.85 | H10: =B10-E10 -> 316800 | I10: 972000 | J10: =B10-E10-I10 -> -655200
A11: 44865 | B11: =C11*D11 -> 7200000 | C11: 450000 | D11: 16 | E11: 6750000 | F11: 5900 | G11: =E11/C11 -> 15 | H11: =B11-E11 -> 450000 | I11: 967500 | J11: =B11-E11-I11 -> -517500
A12: 44895 | B12: =C12*D12 -> 6160000 | C12: 440000 | D12: 14 | E12: 5720000 | F12: 5800 | G12: =E12/C12 -> 13 | H12: =B12-E12 -> 440000 | I12: 966000 | J12: =B12-E12-I12 -> -526000
A13: 44926 | B13: =C13*D13 -> 6300000 | C13: 450000 | D13: 14 | E13: 5854500 | F13: 5750 | G13: =E13/C13 -> 13.01 | H13: =B13-E13 -> 445500 | I13: 967500 | J13: =B13-E13-I13 -> -522000
... A37: 45657 | B37: =C37*D37 -> 10274400 | C37: 720000 | D37: 14.27 | E37: 8712000 | F37: 5700 | G37: =E37/C37 -> 12.1 | H37: =B37-E37 -> 1562400 | I37: 1008000 | J37: =B37-E37-I37 -> 554400

Sheet 存货管理
A1: 日期 | B1: 期初存货_数量（米） | C1: 入库量（米） | D1: 出库量（米） | E1: 期末存货_数量（米） | F1: 单位成本（元） | G1: 存货金额（元） | H1: 月度销售成本 | I1: 存货周转天数
A2: 44592 | B2: 1900000 | C2: 400000 | D2: =销售与成本!C2 -> 550000 | E2: =B2+C2-D2 -> 1750000 | F2: =销售与成本!G2 -> 14.890909 | G2: =E2*F2 -> 26059091 | H2: =销售与成本!E2 -> 8190000 | I2: =((B2+E2)/2)*F2*30/H2 -> 99.545455
A3: 44620 | B3: =E2 -> 1750000 | C3: 370000 | D3: =销售与成本!C3 -> 520000 | E3: =B3+C3-D3 -> 1600000 | F3: =销售与成本!G3 -> 15.05 | G3: =E3*F3 -> 24080000 | H3: =销售与成本!E3 -> 7826000 | I3: =((B3+E3)/2)*F3*30/H3 -> 96.634615
A4: 44651 | B4: =E3 -> 1600000 | C4: 350000 | D4: =销售与成本!C4 -> 500000 | E4: =B4+C4-D4 -> 1450000 | F4: =销售与成本!G4 -> 14.66 | G4: =E4*F4 -> 21257000 | H4: =销售与成本!E4 -> 7330000 | I4: =((B4+E4)/2)*F4*30/H4 -> 91.5
A5: 44681 | B5: =E4 -> 1450000 | C5: 350000 | D5: =销售与成本!C5 -> 480000 | E5: =B5+C5-D5 -> 1320000 | F5: =销售与成本!G5 -> 14.31 | G5: =E5*F5 -> 18889200 | H5: =销售与成本!E5 -> 6868800 | I5: =((B5+E5)/2)*F5*30/H5 -> 86.5625
A6: 44712 | B6: =E5 -> 1320000 | C6: 340000 | D6: =销售与成本!C6 -> 460000 | E6: =B6+C6-D6 -> 1200000 | F6: =销售与成本!G6 -> 14.338261 | G6: =E6*F6 -> 17205913 | H6: =销售与成本!E6 -> 6595600 | I6: =((B6+E6)/2)*F6*30/H6 -> 82.173913
A7: 44742 | B7: =E6 -> 1200000 | C7: 380000 | D7: =销售与成本!C7 -> 450000 | E7: =B7+C7-D7 -> 1130000 | F7: =销售与成本!G7 -> 15.64 | G7: =E7*F7 -> 17673200 | H7: =销售与成本!E7 -> 7038000 | I7: =((B7+E7)/2)*F7*30/H7 -> 77.666667
A8: 44773 | B8: =E7 -> 1130000 | C8: 400000 | D8: =销售与成本!C8 -> 460000 | E8: =B8+C8-D8 -> 1070000 | F8: =销售与成本!G8 -> 14.501739 | G8: =E8*F8 -> 15516861 | H8: =销售与成本!E8 -> 6670800 | I8: =((B8+E8)/2)*F8*30/H8 -> 71.73913
A9: 44804 | B9: =E8 -> 1070000 | C9: 420000 | D9: =销售与成本!C9 -> 470000 | E9: =B9+C9-D9 -> 1020000 | F9: =销售与成本!G9 -> 14.601915 | G9: =E9*F9 -> 14893953 | H9: =销售与成本!E9 -> 6862900 | I9: =((B9+E9)/2)*F9*30/H9 -> 66.702128
A10: 44834 | B10: =E9 -> 1020000 | C10: 450000 | D10: =销售与成本!C10 -> 480000 | E10: =B10+C10-D10 -> 990000 | F10: =销售与成本!G10 -> 14.85 | G10: =E10*F10 -> 14701500 | H10: =销售与成本!E10 -> 7128000 | I10: =((B10+E10)/2)*F10*30/H10 -> 62.8125
A11: 44865 | B11: =E10 -> 990000 | C11: 500000 | D11: =销售与成本!C11 -> 450000 | E11: =B11+C11-D11 -> 1040000 | F11: =销售与成本!G11 -> 15 | G11: =E11*F11 -> 15600000 | H11: =销售与成本!E11 -> 6750000 | I11: =((B11+E11)/2)*F11*30/H11 -> 67.666667
A12: 44895 | B12: =E11 -> 1040000 | C12: 450000 | D12: =销售与成本!C12 -> 440000 | E12: =B12+C12-D12 -> 1050000 | F12: =销售与成本!G12 -> 13 | G12: =E12*F12 -> 13650000 | H12: =销售与成本!E12 -> 5720000 | I12: =((B12+E12)/2)*F12*30/H12 -> 71.25
A13: 44926 | B13: =E12 -> 1050000 | C13: 450000 | D13: =销售与成本!C13 -> 450000 | E13: =B13+C13-D13 -> 1050000 | F13: =销售与成本!G13 -> 13.01 | G13: =E13*F13 -> 13660500 | H13: =销售与成本!E13 -> 5854500 | I13: =((B13+E13)/2)*F13*30/H13 -> 70
A14: 44957 | B14: =E13 -> 1050000 | C14: 480000 | D14: =销售与成本!C14 -> 480000 | E14: =B14+C14-D14 -> 1050000 | F14: =销售与成本!G14 -> 13.52 | G14: =E14*F14 -> 14196000 | H14: =销售与成本!E14 -> 6489600 | I14: =((B14+E14)/2)*F14*30/H14 -> 65.625
... A37: 45657 | B37: =E36 -> 2410000 | C37: 850000 | D37: =销售与成本!C37 -> 720000 | E37: =B37+C37-D37 -> 2540000 | F37: =销售与成本!G37 -> 12.1 | G37: =E37*F37 -> 30734000 | H37: =销售与成本!E37 -> 8712000 | I37: =((B37+E37)/2)*F37*30/H37 -> 103.125

Sheet 应收账款管理
A1: 日期 | B1: 营业收入（元） | C1: 累计营业收入（元） | D1: 应收账款（元） | E1: 应收账款周转率 | F1: 应收账款周转天数
A2: 44592 | B2: =销售与成本!B2 -> 8250000 | C2: 8250000 | D2: 16500000 | E2: =B2/D2 -> 0.5 | F2: =30/E2 -> 60
A3: 44620 | B3: =销售与成本!B3 -> 7961200 | C3: 16211200 | D3: 16300000 | E3: =B3/D3 -> 0.48841718 | F3: =30/E3 -> 61.422901
A4: 44651 | B4: =销售与成本!B4 -> 8680000 | C4: 24891200 | D4: 17100000 | E4: =B4/D4 -> 0.50760234 | F4: =30/E4 -> 59.101382
A5: 44681 | B5: =销售与成本!B5 -> 7492800 | C5: 32384000 | D5: 17800000 | E5: =B5/D5 -> 0.42094382 | F5: =30/E5 -> 71.268418
A6: 44712 | B6: =销售与成本!B6 -> 7442800 | C6: 39826800 | D6: 18000000 | E6: =B6/D6 -> 0.41348889 | F6: =30/E6 -> 72.55334
A7: 44742 | B7: =销售与成本!B7 -> 7798500 | C7: 47625300 | D7: 18300000 | E7: =B7/D7 -> 0.42614754 | F7: =30/E7 -> 70.398153
A8: 44773 | B8: =销售与成本!B8 -> 8270800 | C8: 55896100 | D8: 18500000 | E8: =B8/D8 -> 0.44707027 | F8: =30/E8 -> 67.103545
A9: 44804 | B9: =销售与成本!B9 -> 7458900 | C9: 63355000 | D9: 18200000 | E9: =B9/D9 -> 0.40982967 | F9: =30/E9 -> 73.201142
A10: 44834 | B10: =销售与成本!B10 -> 7444800 | C10: 70799800 | D10: 18000000 | E10: =B10/D10 -> 0.4136 | F10: =30/E10 -> 72.533849
A11: 44865 | B11: =销售与成本!B11 -> 7200000 | C11: 77999800 | D11: 17500000 | E11: =B11/D11 -> 0.41142857 | F11: =30/E11 -> 72.916667
A12: 44895 | B12: =销售与成本!B12 -> 6160000 | C12: 84159800 | D12: 16800000 | E12: =B12/D12 -> 0.36666667 | F12: =30/E12 -> 81.818182
A13: 44926 | B13: =销售与成本!B13 -> 6300000 | C13: 90459800 | D13: 16500000 | E13: =B13/D13 -> 0.38181818 | F13: =30/E13 -> 78.571429
... A37: 45657 | B37: =销售与成本!B37 -> 10274400 | C37: 316508200 | D37: 27500000 | E37: =B37/D37 -> 0.37361455 | F37: =30/E37 -> 80.29666

Sheet 现金周期
A1: 日期 | B1: 存货周转天数 | C1: 应收账款周转天数 | D1: 应付账款周转天数 | E1: 现金周期（天）
A2: 44592 | B2: =存货管理!I2 -> 99.545455 | C2: =应收账款管理!F2 -> 60 | D2: 45 | E2: =B2+C2-D2 -> 114.54545
A3: 44620 | B3: =存货管理!I3 -> 96.634615 | C3: =应收账款管理!F3 -> 61.422901 | D3: 45 | E3: =B3+C3-D3 -> 113.05752
A4: 44651 | B4: =存货管理!I4 -> 91.5 | C4: =应收账款管理!F4 -> 59.101382 | D4: 45 | E4: =B4+C4-D4 -> 105.60138
A5: 44681 | B5: =存货管理!I5 -> 86.5625 | C5: =应收账款管理!F5 -> 71.268418 | D5: 45 | E5: =B5+C5-D5 -> 112.83092
A6: 44712 | B6: =存货管理!I6 -> 82.173913 | C6: =应收账款管理!F6 -> 72.55334 | D6: 45 | E6: =B6+C6-D6 -> 109.72725
A7: 44742 | B7: =存货管理!I7 -> 77.666667 | C7: =应收账款管理!F7 -> 70.398153 | D7: 45 | E7: =B7+C7-D7 -> 103.06482
A8: 44773 | B8: =存货管理!I8 -> 71.73913 | C8: =应收账款管理!F8 -> 67.103545 | D8: 45 | E8: =B8+C8-D8 -> 93.842675
A9: 44804 | B9: =存货管理!I9 -> 66.702128 | C9: =应收账款管理!F9 -> 73.201142 | D9: 45 | E9: =B9+C9-D9 -> 94.90327
A10: 44834 | B10: =存货管理!I10 -> 62.8125 | C10: =应收账款管理!F10 -> 72.533849 | D10: 45 | E10: =B10+C10-D10 -> 90.346349
A11: 44865 | B11: =存货管理!I11 -> 67.666667 | C11: =应收账款管理!F11 -> 72.916667 | D11: 45 | E11: =B11+C11-D11 -> 95.583333
A12: 44895 | B12: =存货管理!I12 -> 71.25 | C12: =应收账款管理!F12 -> 81.818182 | D12: 50 | E12: =B12+C12-D12 -> 103.06818
A13: 44926 | B13: =存货管理!I13 -> 70 | C13: =应收账款管理!F13 -> 78.571429 | D13: 50 | E13: =B13+C13-D13 -> 98.571429
... A37: 45657 | B37: =存货管理!I37 -> 103.125 | C37: =应收账款管理!F37 -> 80.29666 | D37: 50 | E37: =B37+C37-D37 -> 133.42166
